pipecheck/__init__.py
pipecheck/__main__.py
pipecheck/api.py
pipecheck/checks/__init__.py
pipecheck/checks/dns.py
pipecheck/checks/http.py
pipecheck/checks/icmp.py
pipecheck/checks/mysql.py
pipecheck/checks/tcp.py
pipecheck/cli.py
pipecheck/cli_backport.py
pipecheck/cmdfile.py
pipecheck/utils.py
pipecheck-0.4.2.dist-info/LICENSE
pipecheck-0.4.2.dist-info/METADATA
pipecheck-0.4.2.dist-info/WHEEL
pipecheck-0.4.2.dist-info/RECORD
